easyquery_query_builder/__init__.py
easyquery_query_builder/queries/__init__.py
easyquery_query_builder/queries/query.py
easyquery_query_builder/queries/read_query.py
easyquery_query_builder/queries/read_query_builder.py
easyquery_query_builder/queries/read_query_with_joins.py
easyquery_query_builder/queries/read_query_with_joins_builder.py
easyquery_query_builder-2.0.1.dist-info/METADATA
easyquery_query_builder-2.0.1.dist-info/WHEEL
easyquery_query_builder-2.0.1.dist-info/RECORD
