Metadata-Version: 2.1
Name: easyquery-query-builder
Version: 2.0.1
Summary: 
Author: Smolke
Author-email: d.smolczynski1@gmail.com
Requires-Python: >=3.11,<4.0
Classifier: Programming Language :: Python :: 3
Classifier: Programming Language :: Python :: 3.11
Requires-Dist: easyvalid-data-validator (>=2.0.1,<3.0.0)
